aiodnsresolver.py
aiodnsresolver-0.0.157.dist-info/METADATA
aiodnsresolver-0.0.157.dist-info/WHEEL
aiodnsresolver-0.0.157.dist-info/licenses/LICENSE
aiodnsresolver-0.0.157.dist-info/RECORD
