Metadata-Version: 2.4
Name: aiodnsresolver
Version: 0.0.157
Summary: Pure asyncio Python DNS resolver
Project-URL: Homepage, https://github.com/michalc/aiodnsresolver
Author-email: Gerald <i@gerald.top>, Michal Charemza <michal@charemza.name>
License-Expression: MIT
License-File: LICENSE
Classifier: Intended Audience :: Developers
Classifier: License :: OSI Approved :: MIT License
Classifier: Programming Language :: Python :: 3 :: Only
Classifier: Programming Language :: Python :: 3.6
Classifier: Programming Language :: Python :: 3.7
Classifier: Topic :: Internet :: Name Service (DNS)
Requires-Python: >=3.6.4
Provides-Extra: lint
Requires-Dist: pre-commit; extra == 'lint'
Requires-Dist: pylint; extra == 'lint'
Provides-Extra: test
Requires-Dist: aiofastforward; extra == 'test'
Requires-Dist: aiohttp; extra == 'test'
Requires-Dist: pytest; extra == 'test'
Requires-Dist: pytest-cov; extra == 'test'
